llama_index/readers/macrometa_gdn/__init__.py
llama_index/readers/macrometa_gdn/base.py
llama_index_readers_macrometa_gdn-0.4.1.dist-info/METADATA
llama_index_readers_macrometa_gdn-0.4.1.dist-info/WHEEL
llama_index_readers_macrometa_gdn-0.4.1.dist-info/licenses/LICENSE
llama_index_readers_macrometa_gdn-0.4.1.dist-info/RECORD
