Metadata-Version: 2.4
Name: llama-index-readers-macrometa-gdn
Version: 0.4.1
Summary: llama-index readers macrometa_gdn integration
Author-email: Your Name <you@example.com>
Maintainer: Dain Im
License-Expression: MIT
License-File: LICENSE
Keywords: macrometa
Requires-Python: <4.0,>=3.9
Requires-Dist: llama-index-core<0.15,>=0.13.0
